twarc2sql/__init__.py
twarc2sql/twarc2sql.py
twarc2sql/db_utils/__init__.py
twarc2sql/db_utils/db_access.py
twarc2sql/db_utils/models.py
twarc2sql/db_utils/tests/__init__.py
twarc2sql/db_utils/tests/conftest.py
twarc2sql/db_utils/tests/test_db_access.py
twarc2sql/file_utils/__init__.py
twarc2sql/file_utils/file_to_object.py
twarc2sql/file_utils/file_utils.py
twarc2sql/file_utils/object_to_table.py
twarc2sql-1.0.0.dist-info/AUTHORS.rst
twarc2sql-1.0.0.dist-info/LICENSE
twarc2sql-1.0.0.dist-info/METADATA
twarc2sql-1.0.0.dist-info/WHEEL
twarc2sql-1.0.0.dist-info/top_level.txt
twarc2sql-1.0.0.dist-info/RECORD
